strava_connector/__init__.py
strava_connector/authenticator.py
strava_connector/connector.py
strava_connector-0.2.2.dist-info/LICENSE
strava_connector-0.2.2.dist-info/METADATA
strava_connector-0.2.2.dist-info/WHEEL
strava_connector-0.2.2.dist-info/RECORD
