Metadata-Version: 2.1
Name: strava_connector
Version: 0.2.2
Summary: Simple Strava client written in Python
Home-page: https://github.com/thomascamminady/strava_connector
Author: Thomas Camminady
Author-email: 0milieux_member@icloud.com
Requires-Python: >=3.9,<3.12
Classifier: Programming Language :: Python :: 3
Classifier: Programming Language :: Python :: 3.9
Classifier: Programming Language :: Python :: 3.10
Classifier: Programming Language :: Python :: 3.11
Requires-Dist: requests (>=2.31.0,<3.0.0)
Project-URL: Documentation, https://camminady.dev/strava_connector/strava_connector/connector.html
Project-URL: Repository, https://github.com/thomascamminady/strava_connector
